techiaith/py.typed
techiaith/mimic/cli.py
techiaith/mimic/dataset.py
techiaith/mimic/inference.py
techiaith/mimic/schema.py
techiaith/mimic/ui.py
techiaith_mimic-2025.1.27.dev1.dist-info/LICENSE
techiaith_mimic-2025.1.27.dev1.dist-info/METADATA
techiaith_mimic-2025.1.27.dev1.dist-info/WHEEL
techiaith_mimic-2025.1.27.dev1.dist-info/entry_points.txt
techiaith_mimic-2025.1.27.dev1.dist-info/top_level.txt
techiaith_mimic-2025.1.27.dev1.dist-info/RECORD
